Metadata-Version: 1.2
Name: pycopy-cpython-upip
Version: 1.3.3
Summary: Pycopy module upip ported to CPython
Home-page: https://github.com/pfalcon/pycopy-lib
Author: Paul Sokolovsky
Author-email: pycopy-dev@googlegroups.com
Maintainer: Paul Sokolovsky
Maintainer-email: pycopy-dev@googlegroups.com
License: Python
Platform: UNKNOWN
